{"page": 136, "max_verse": 43, "full_list": [24, 25, 26, 27, 28, 29, 30, 31, 32, 33, 34, 35, 36, 37, 38, 39, 40, 41, 42, 43], "alternatives": [], "chapter_starts_here": false, "confidence": "high", "notes": "", "raw": "{\n  \"verses\": [\n    {\n      \"n\": 24,\n      \"column\": \"left\",\n      \"text\": \"Un fchee irr Zibe\u00f6na Deh-\\\\\\nli/ Ajus un Anus/ schis irr tas\\\\\\nAnus/ kas tohs Strg\u00b7 Ehsetus\\\\\\nZukneji irr tsdohmais/ kad\\\\\\nwi\ua7a5sch Satva Tehwa Zibe\u00f6na Eh-\\\\\\nsetus gannija.\\n\"\n    },\n    {\n      \"n\": 25,\n      \"column\": \"left\",\n      \"text\": \"Un fchee irr Anus Dehli/\\\\\\nDisons/ un A\u00e4ltbama btja A-\\\\\\nnus Metta.\\n\"\n    },\n    {\n      \"n\": 26,\n      \"column\": \"left\",\n      \"text\": \"Un fchee irr Disona Deh-\\\\\\nli/ Eimdans/ un Esbans/ un Je-\\\\\\ntrans/ un Karans.\\n\"\n    },\n    {\n      \"n\": 27,\n      \"column\": \"left\",\n      \"text\": \"Schee irr Ezera Dehli/\\\\\\nBilans/ un Saiwans/ un Akans.\\n\"\n    },\n    {\n      \"n\": 28,\n      \"column\": \"left\",\n      \"text\": \"Schee irr Disana Dehli/\\\\\\nUz/ un Arans.\\n\"\n    },\n    {\n      \"n\": 29,\n      \"column\": \"left\",\n      \"text\": \"Schee irr to Oritervu\\\\\\nWaldneeki/ tas Waldneeks Lo-\\\\\\ntans/ tas Waldneeks Sobals/\\\\\\ntas Waldneeks Zibe\u00f6ns/ tas\\\\\\nWaldneeks Anus.\\n\"\n    },\n    {\n      \"n\": 30,\n      \"column\": \"left\",\n      \"text\": \"Tas Waldneeks Disons/\\\\\\ntas Waldneeks Ezers/ tas Wald-\\\\\\nneeks Disans/ schee irr to Orite-\\\\\\nru Waldneeki pehz fawahm Wal-\\\\\\nftibahm eefsch Seires Semnes.\\n\"\n    },\n    {\n      \"n\": 31,\n      \"column\": \"left\",\n      \"text\": \"Un schee irr tee Rehnixi/\\\\\\npas waldijfchi eefsch Gedoma\\\\\\nSemnes/ pirns ne ka weens\\\\\\nRebutascb waldija pahr Isra\u00ebta\\\\\\nBehrneem.\\n\"\n    },\n    {\n      \"n\": 32,\n      \"column\": \"left\",\n      \"text\": \"Betue/ Beora Dehls wal-\\\\\\ndija eefsch Gedoma/ un winna\\\\\\nPilsfahba Wahrs bija Dinaba.\\n\"\n    },\n    {\n      \"n\": 33,\n      \"column\": \"left\",\n      \"text\": \"Un Belus nomirre/ un\\\\\\nwinna Weet\u00e2 waldija Jobabs/\\\\\\nSerus Dedis no Bazras.\\n\"\n    },\n    {\n      \"n\": 34,\n      \"column\": \"left\",\n      \"text\": \"Un Jobabs nomirre/ un\\\\\\nwinna Weet\u00e2 waldija Usans/\\\\\\nno to Teemanitren Semnes.\\n\"\n    },\n    {\n      \"n\": 35,\n      \"column\": \"right\",\n      \"text\": \"Un Usans nomir\\\\\\nwinna Weet\u00e2 waldija\\\\\\nBedada Dehls/ kas M\\\\\\nMo\u00e4ba Lauk\u00e4 apfawe/\\\\\\nna PilsfahtaWahrds bija\\n\"\n    },\n    {\n      \"n\": 36,\n      \"column\": \"right\",\n      \"text\": \"Un Adads nomir\\\\\\nwinna Weet\u00e2 waldija \ufffd\\\\\\nno Masrekas.\\n\"\n    },\n    {\n      \"n\": 37,\n      \"column\": \"right\",\n      \"text\": \"Un Samlus nomir\\\\\\nwinna Weet\u00e2 waldija \ufffd\\\\\\nno Re\u00f6botes pee tahs Up\\n\"\n    },\n    {\n      \"n\": 38,\n      \"column\": \"right\",\n      \"text\": \"Un Sauls nomir\\\\\\nwinna Weet\u00e2 waldija \ufffd\\\\\\nnans/ Akbora Dehls.\\n\"\n    },\n    {\n      \"n\": 39,\n      \"column\": \"right\",\n      \"text\": \"Un B\u00e5l-Anans/\\\\\\nDehls nomirre/ un win\\\\\\nt\u00e4 waldija Adars/ un\\\\\\nPilsfahta Wahrs bija \ufffd\\\\\\nun winna Seewas Wah\\\\\\nMe\u00ebtabe\u00eble/ Matredas\\\\\\ntahs Meitas Mes\u00e4bas.\\n\"\n    },\n    {\n      \"n\": 40,\n      \"column\": \"right\",\n      \"text\": \"Un schee irr Gesarw\\\\\\nneeku Wahrdi/pehz fawee\\\\\\ndeem/ pehz fawahm We\\\\\\nar faween Wahrdeen\\\\\\nWaldneeks Timmus/ tas\\\\\\nneeks Ativus/ tas W\\\\\\nJetets.\\n\"\n    },\n    {\n      \"n\": 41,\n      \"column\": \"right\",\n      \"text\": \"Tas Waldneeks\\\\\\nmus/ tas Waldneeks Ecl\\\\\\nWaldneeks Pinons.\\n\"\n    },\n    {\n      \"n\": 42,\n      \"column\": \"right\",\n      \"text\": \"Tas Waldneeks\\\\\\ntas Waldneeks Teeman\\\\\\nWaldneeks Mibzars.\\n\"\n    },\n    {\n      \"n\": 43,\n      \"column\": \"right\",\n      \"text\": \"Tas Waldneeks Ma\\\\\\ntas Waldneeks Jbrams.\\\\\\nirr Gedoma Waldneeki/\\\\\\nween Kaddeem/ eefsch\\\\\\nGemantofkhanaeSemnes\\\\\\nfaws irr to Gedomiren \ufffd\\n\"\n    }\n  ],\n  \"confidence\": \"high\",\n  \"notes\": \"\"\n}", "error": ""}