{"page": 239, "max_verse": 10, "full_list": [2, 3, 4, 5, 6, 7, 8, 2, 5, 6, 7, 8, 9, 10], "alternatives": [], "chapter_starts_here": false, "confidence": "high", "notes": "", "raw": "{\n  \"verses\": [\n    {\n      \"n\": 2,\n      \"column\": \"left\",\n      \"text\": \"Un kad manna Gohdiba\\\\\\nreecs/ tad li\u017f\u017fchu es teu Ak-\\\\\\nu Starpun\u00e2 stahweht/ un\\\\\\nupflah\u017fchu tew ar mannu Roh-\\\\\\ntee\u017fams es e\u017fmu pahrgahjts.\\n\"\n    },\n    {\n      \"n\": 3,\n      \"column\": \"left\",\n      \"text\": \"Un kad es fatwu Rohku\\\\\\nattehuis/ tad tu mann re-\\\\\\nno pakakenes/ bet mans\\\\\\ngs ne warr red\u017fehts tapt.\\n\"\n    },\n    {\n      \"n\": 4,\n      \"column\": \"left\",\n      \"text\": \"a XXXIV. Nodalla.\\ndarra us Deewa Pawehlefchanu diwi\\\\\\nakminaiaus Galdus: 1. Kahpj us to\\\\\\nu: 4. Luhds/ ka Deews gribbohts ar\\\\\\neem lihds ret: 9. us to atjauna Deews\\\\\\nerribu ar teem kaudim. 10. Ta/ ka\\\\\\nne buhs ar teem Pagareem feb Elkeem\\\\\\ndrinatees: 12. Lee Bausli no Leel-\\\\\\nas Swehtkeem: 18. No teem Pirm-\\\\\\nnascheem: 19. No Ewehdeenas: 21.\\\\\\nBasaras/ un Leeweno Swehtku Turre.\\\\\\n8: 22. Mohsus gave 40. Deenas un\\\\\\naktis: 28. Leek weenu Apjeggu pree\u017fch\\\\\\nfoh\u017fchu Waigu: 29.\\n\"\n    },\n    {\n      \"n\": 5,\n      \"column\": \"left\",\n      \"text\": \"Ad fazzija tas KUNgs\\\\\\nus Mohsu: Iszehrtees/\\\\\\ndiwi Akmira Galdus/\\\\\\nohs pirmajus/ tad raksti-\\\\\\nus teem Galdeem tohs\\\\\\nus/ kas us teem pirma-\\\\\\naldeem irr bijuschi/ ko tu\\\\\\nsijs.\\n\"\n    },\n    {\n      \"n\": 6,\n      \"column\": \"left\",\n      \"text\": \"teffi rihtu gattaws/ ka tu\\\\\\nrii uskahpt us to Kalnu\\\\\\nin stahjees mann\u00e2 Breek-\\\\\\nus ta Kalna Gallu.\\n\"\n    },\n    {\n      \"n\": 7,\n      \"column\": \"left\",\n      \"text\": \"ue weenam buhs ar teew\\\\\\nkahpt/ ne weenam arri\\\\\\nsetam tapt ap to wi\u017f\u017fu\\\\\\ned\u017ftihkeem/ ned\u00ea leelem\\\\\\nbuhs tam Kalnam pret-\\\\\\neem tapt.\\n\"\n    },\n    {\n      \"n\": 8,\n      \"column\": \"left\",\n      \"text\": \"d iszirte wi\u017f\u017fch diwi Ak-\\\\\\n\"\n    },\n    {\n      \"n\": 2,\n      \"column\": \"right\",\n      \"text\": \"minza Galdinus/ itt ka' tohs pir-\\\\\\nmajus/ un Mohsus zehlahs Rihta\\\\\\nagri/ un kahpe aug\u017fcham us to\\\\\\nKalnu Sinai/ ittin ka tas\\\\\\nKUNGStam bij pawehlejs/ un\\\\\\nwinsch nehme fatw\u00e2 Rohka tohs\\\\\\ndiwi Akmira Galdinus.\\n\"\n    },\n    {\n      \"n\": 5,\n      \"column\": \"right\",\n      \"text\": \"Tad nonahze tas KUNGS\\\\\\nweena Padebbeti/ un peestabjahs\\\\\\ntur pee winna/ un winsch jauze\\\\\\nar Wahrdn/ KUNGS.\\n\"\n    },\n    {\n      \"n\": 6,\n      \"column\": \"right\",\n      \"text\": \"Un tas KUNGS pagahje\\\\\\npree\u017fch winna fezzen/ un fanze/\\\\\\nKUNGS/KUNGS/GTIP-\\\\\\nRAJS DEEWS/schehligajs/\\\\\\nfirdsmihligajs/ un lehnprahti-\\\\\\ngajs/ un leels no Labdarrischa-\\\\\\nnas/ un Pateefibas/\\n\"\n    },\n    {\n      \"n\": 7,\n      \"column\": \"right\",\n      \"text\": \"Turredams Labprahtibu\\\\\\npee dauds tuhk\u017ftoscheem/ peedoh-\\\\\\ndamsRoseegunu/Pahrkahptcha-\\\\\\nnas un * Grehkus/ un (tomehr\\\\\\nGrehkus) nejo\u017fditus ne pa-\\\\\\nmett: Peemekledams to Tehwu\\\\\\nGrehkus pee teem Behrnein/ un\\\\\\npee teem Behrnu Behrneem lihds\\\\\\ntrefscham un zettortun (Augu-\\\\\\nmam.\\n\"\n    },\n    {\n      \"n\": 8,\n      \"column\": \"right\",\n      \"text\": \"* Tas irr: Winsch peedohd Grehkus, bet\\\\\\nzittadi ne, ka ween us Kriftus Ganndarri\u017fchanu\\\\\\nredsedams, kas muhfo Grehku deht eewai-\\\\\\nnohts, us ko Deews to Sohdibu lizzis, Efar-\\\\\\n13, 5. Ka tas tai\u017fns egus, un tai\u017fnu darra to,\\\\\\nkas no tahs Tizzibas Jesus irr. Reem: 3, 26.\\\\\\n2. Kor: 5, 12.\\n\"\n    },\n    {\n      \"n\": 9,\n      \"column\": \"right\",\n      \"text\": \"Un Mohsus tranzahs/ un\\\\\\nleezahs pee Seines/ un peeluhdse.\\\\\\n\"\n    },\n    {\n      \"n\": 10,\n      \"column\": \"right\",\n      \"text\": \"Un winsch fazzija: Kungs/\\\\\\nja es/ luhsams/ Schehlastibu\\\\\\nesmu atraddis tawas Azzis/ tad\\\\\\neij jelle Kungs lihds ar numbs/\\\\\\njep\u017fchu \u017fchee irr pahrgalwigi Lau-\\\\\\ndis/\\n\"\n    }\n  ],\n  \"confidence\": \"high\",\n  \"notes\": \"\"\n}", "error": ""}