{"page": 295, "max_verse": 16, "full_list": [6, 7, 8, 9, 10, 11, 12, 13, 14, 15, 16], "alternatives": [], "chapter_starts_here": false, "confidence": "high", "notes": "", "raw": "```json\n{\n  \"verses\": [\n    {\n      \"n\": 6,\n      \"column\": \"left\",\n      \"text\": \"6. Un tain Preesteram buhs\\nGr: to Affini us ta KUNGA Altari\\npreek\u017fch tahs Sa-eeschanas Telts\\nGr: Durwin flazziht / un winnam\\nbuhs tohs Taurus eeded\u017finaht par\\nfaldu Smarschu tain KUN-\\nGAM.\\n\"\n    },\n    {\n      \"n\": 7,\n      \"column\": \"left\",\n      \"text\": \"7. Teem arri ne buhs wairs\\nGr: favus Uppurus teem Johdeem\\nuppureht/kam tee irr paklatmanu-\\nkoj\u017fcht / lai tas winneem par Lit-\\nGr: kunn irr pee favweem Pehznahka-\\nGr: meem muhschaun.\\n\"\n    },\n    {\n      \"n\": 8,\n      \"column\": \"left\",\n      \"text\": \"8. Saffi tad us winneem:\\nJeweens no Isra\u00ebta Namma/ un\\n8, no teem Swechineekeem/kas juh-\\n16, fu Starp\u00e2 ka Swechineeki mah-\\njo/kad tas weenu Dedfamu-Uppu-\\n19, ri/ jeb zittu Uppuri grib uppureht.\\n\"\n    },\n    {\n      \"n\": 9,\n      \"column\": \"left\",\n      \"text\": \"9. Un ne nefihs to preek\u017fch tahs\\nSa-eeschanas Telts Durwin/fa-\\nta\u017fjidams to paschu tam KUN-\\nGAM / tain paschain Wihrarn\\nbuhs isdeldetam tapt no favweem\\nLandim.\\n\"\n    },\n    {\n      \"n\": 10,\n      \"column\": \"left\",\n      \"text\": \"10. Un i\u017fweens no Isra\u00ebta\\nNanna/un no teem Swechinee-\\nGr: keem/ kas juhu Starp\u00e2 ka Swe-\\nGr: schineeki mahjo / kas jeb kahdu\\nAffini ehdihs / prett to paschu/\\nkas to Affini ehdihs/zelfchu es fa-\\nwu Wainu / un isdeldefchu to no\\nfavweem Landim.\\n\"\n    },\n    {\n      \"n\": 11,\n      \"column\": \"left\",\n      \"text\": \"11. Jo tahs Mee\u017fas Dsihwiba\\n\"\n    },\n    {\n      \"n\": 12,\n      \"column\": \"right\",\n      \"text\": \"12. Tadeht efimu es Isra\u00ebta\\nBehrneem fazztijs: Ne weenam no\\njums buhs Affini eh\u017ft / ned\u00df arri\\ntam Swechineekam / kas juhfu\\nStarp\u00e2 ka Swechineeks mahjo\\nbuhs Affini eh\u017ft.\\n\"\n    },\n    {\n      \"n\": 13,\n      \"column\": \"right\",\n      \"text\": \"13. Iffatram no Isra\u00ebta\\nBehrneem/ un no teem Swechi-\\nneekem / kas juhfu Starp\u00e2 ka\\nSwechineeki mahjo / kas kahdu\\nMescha Swehru jeb Putui med-\\ndi / kas ehdaits irr / tam buhs\\nwinna Affini isleet / un to ar\\nSemmi apraust.\\n\"\n    },\n    {\n      \"n\": 14,\n      \"column\": \"right\",\n      \"text\": \"14. Jo tas Affins irr wi\ufb00ae\\nMeefas Dsihwiba / zee\u017fams ta-\\ndsihwo/tapehz efimu es teem Isra-\\n\u00ebta Behrneem fazzijs / jums ne\\nbuhs ne kahdas Mee\u017fas Affin-\\neh\u017ft / jo wi\ufb00as Mee\u017fas Dsihwib-\\nirr winnas Affins / wi\ufb00am / ka-\\nto ehd buhs tsdeldetam tapt.\\n\"\n    },\n    {\n      \"n\": 15,\n      \"column\": \"right\",\n      \"text\": \"15. Un kursch starp teem / ka-\\ntai Semm\u00ea dsimmufschi/ jeb star-\\nteem Swechineekeem weenu Mat-\\ntu jeb faplohtiitu ehd / tam buhs ta-\\nwas Drehe\u00df masgaht / un ar Uh-\\ndeni pehrtees / uu neschkihstaun\\nbuht lihds Waftaram/tad wi\u017fch-\\nschkihsts taps.\\n\"\n    },\n    {\n      \"n\": 16,\n      \"column\": \"right\",\n      \"text\": \"16. Bet ja wi\u017fch (tahs) ni-\\nmasgaht/neds favu Mee\u017fu pehrs-\\ntad buhs winnam favu Noseegu-\\nmu nest.\\n\"\n    }\n  ],\n  \"confidence\": \"high\",\n  \"notes\": \"\"\n}\n```", "error": ""}