{"page": 470, "max_verse": 29, "full_list": [21, 22, 23, 24, 25, 26, 27, 28, 29, 1], "alternatives": [], "chapter_starts_here": false, "confidence": "high", "notes": "", "raw": "```json\n{\n  \"verses\": [\n    {\n      \"n\": 21,\n      \"column\": \"left\",\n      \"text\": \"Un tas KUNGS atschkirs\\nwinan par Zaununu no wi\u017f\u017fahm\\nIsra\u00ebta Ziltim / pehz wi\u017f\u017feem\\nDerribas Wahrdeem/ kas fchinni\\nBautlibas-Grahmata rakftiti irr.\\n\"\n    },\n    {\n      \"n\": 22,\n      \"column\": \"left\",\n      \"text\": \"Tad fazzihs tee pehznah-\\nkamee Augunti juhsu Behrnt/kas\\npakkat junis zelfees/un tas Swe-\\nfchajs / kas no tahtas Semmes\\nnahks/ kad tee redsehs tahs Semi-\\nmes Mohzibas/un winnasSehr-\\ngas/ ar fo tas KUNGS winnu\\nliks firgt.\\n\"\n    },\n    {\n      \"n\": 23,\n      \"column\": \"left\",\n      \"text\": \"Ka wi\u017f\u017fa winna Semme\\neffoti Sehrs un deggohts Sahls/\\nka ta ne warr apfehta tapt/ un ne\\nfattohs / un ne kahda Sahte no\\ntahs isaugis/lihds ka eek\u017fch Sodo-\\nmas un Gomorras/ Ahdamas un\\nZebotma Isdeldefchanas / fo tas\\nKUNGS irr isdeldejs farva Duf-\\nmiba un Bahrsiba.\\n\"\n    },\n    {\n      \"n\": 24,\n      \"column\": \"left\",\n      \"text\": \"Tad fazzihs wi\u017f\u017fi Laudis:\\nkahez irr tas KUNGS fchai\\nSemmei ta darrijs ? kas ta par\\nleela Bahrsiba tahdas Dufino-\\nfchanas?\\n\"\n    },\n    {\n      \"n\": 25,\n      \"column\": \"left\",\n      \"text\": \"Tad fazzihs winni/tapehz\\nka tee ta KUNGA farvu Tehwu\\nDeewa Derribu irr atstahjuschi /\\nfo wi\u017f\u017fch ar teem bij darrijs / kad\\nwi\u017f\u017fch tohs no Egiptes-Semmes\\ni\u017fwedde.\\n\"\n    },\n    {\n      \"n\": 26,\n      \"column\": \"left\",\n      \"text\": \"Un irr nogahjuschi/un zit-\\n\"\n    },\n    {\n      \"n\": 27,\n      \"column\": \"right\",\n      \"text\": \"Tapehz irr ta KUNGS\\nBahrsiba ap\u017fkaitintees prett fch-\\nSemmi / wi\u017f\u017fus fchohs Lahstu\\npahr winnu west / kas fchinn\\nGrahmata rakftiti irr.\\n\"\n    },\n    {\n      \"n\": 28,\n      \"column\": \"right\",\n      \"text\": \"Un tas KUNGS irr toh\\nno winnu Semmes i\u017f\u017fuhmis/a\\nDusnibu / ar Bahrsibu/ un a\\nleelu Ap\u017fkaifchannu / un irr toh\\ni\u017fmettis us weenu zittu Semmi\\nittin ka tas fchodeen irr.\\n\"\n    },\n    {\n      \"n\": 29,\n      \"column\": \"right\",\n      \"text\": \"Ir ta KUNGA muhfi\\nDeewa Notlehpumi irr finnam\\ndarriti/muns un muhfein Bebr-\\nneem muhscham / ka mums wi-\\nfus fchohs Bautlibas Wahrdue\\nbuhs darrtht.\\n\"\n    },\n    {\n      \"n\": 1,\n      \"column\": \"right\",\n      \"text\": \"teem Deewem kalpojschi /\\nwinnus pceluhguschi/tahdus Dee-\\nwus/ kas tohs ne pasihst/ un teem\\nne neeka irr eedewuschl.\\n\"\n    }\n  ],\n  \"confidence\": \"high\",\n  \"notes\": \"\"\n}\n```", "error": ""}