{"page": 966, "max_verse": 14, "full_list": [1, 2, 3, 4, 5, 6, 6, 7, 8, 1, 9, 10, 11, 12, 13, 14], "alternatives": [], "chapter_starts_here": false, "confidence": "high", "notes": "", "raw": "{\n  \"verses\": [\n    {\n      \"n\": 1,\n      \"column\": \"left\",\n      \"text\": \"Ad fazzija Salamans: \\\\\\nTas KUNGS irr faz- \\\\\\nzijs/ wi\ua7a5\u017fch griboohts \\\\\\neek\u017fch Pakreh\u017flibas d\u017fthwoht.\"\n    },\n    {\n      \"n\": 2,\n      \"column\": \"left\",\n      \"text\": \"Un es efinu tew weenu \\\\\\nMahja\u017f-Weetu darrijs/ un wee- \\\\\\nnu Weetu tew par muhschign \\\\\\nMifchanu.\"\n    },\n    {\n      \"n\": 3,\n      \"column\": \"left\",\n      \"text\": \"Pehz atgreese tas Kehni\u017fch \\\\\\ntawn Waigu/ un \u017fwehtija wi\ua7a5\u017f- \\\\\\nfu Isra\u00ebta Draud\u017fi/ un wi\ufb00a \\\\\\nIsra\u00ebta Draud\u017fe \u017ftahweja.\"\n    },\n    {\n      \"n\": 4,\n      \"column\": \"left\",\n      \"text\": \"Un wi\ua7a5\u017fch fazzija: Sla- \\\\\\nwehts laid irr tas KUNGS I- \\\\\\nfra\u00ebta Deews/ kas ar fawu \\\\\\nMutti us mannu Tehwu Dah- \\\\\\nwidu irr runnajs/ un ar fawu \\\\\\nRohku peepildijs/ un fazzijis:\"\n    },\n    {\n      \"n\": 5,\n      \"column\": \"left\",\n      \"text\": \"No tahs Deenas/ kamehr\"\n    },\n    {\n      \"n\": 6,\n      \"column\": \"left\",\n      \"text\": \"es \u017fawus Laudi\u017f no Egiptes- \\\\\\nSemnes efinu i\u017fweddjs/ ne ef- \\\\\\nmu es ne kahdn Pilsfahtu i\u017f- \\\\\\nwehlejs no wi\u017ffahm Isra\u00ebta Zil- \\\\\\ntim/ weenu Nammu taifiht/ ka \\\\\\nmans Wahrd\u1e63 tur buhtn/es ar- \\\\\\nri ne e\u017fmu ne kahdn Wihru i\u017f- \\\\\\nredscjs/ kas par Walditaju pahr \\\\\\nmaneem Isra\u00ebta Landim buhtu.\"\n    },\n    {\n      \"n\": 6,\n      \"column\": \"left\",\n      \"text\": \"Bet Jerufalemi e\u017fmu es \\\\\\ni\u017fwehlejs/ ka tur mans Wahrd\u1e63 \\\\\\nbuhtu/ un Dahwidu e\u017fmu es i\u017f- \\\\\\nwehlejs/ ka tas pahr manneem \\\\\\nIsra\u00ebta Landim buhtu.\"\n    },\n    {\n      \"n\": 7,\n      \"column\": \"left\",\n      \"text\": \"Un tas gann mannam Teh- \\\\\\nwam Dahwidam Sir\u1e0di bija ta \\\\\\nKUNGA Isra\u00ebta Deewa Wah\u1e5b- \\\\\\ndam weenu Nammu darriht/\"\n    },\n    {\n      \"n\": 8,\n      \"column\": \"left\",\n      \"text\": \"Bet tas KUNGS fazzija \\\\\\nus mannu Tehwu Dahwidu: \\\\\\nTapehz ka tu taiwa Sir\u1e0di efi\"\n    },\n    {\n      \"n\": 1,\n      \"column\": \"right\",\n      \"text\": \"apnehmees mannam Wah\u1e5b- \\\\\\nweenu Nammu darriht/ e\ufb00 \\\\\\ngann labbi darrijs/ ka tas ta \\\\\\nSir\u1e0di bijis irr.\"\n    },\n    {\n      \"n\": 9,\n      \"column\": \"right\",\n      \"text\": \"Tomehr tew ne buhe \\\\\\nNammu patai\u017fiht/ bet ta \\\\\\nDehls/ kas no taweem Gurn \\\\\\nnahks/ tas ustaifibs manr \\\\\\nWahrdam to Nammu.\"\n    },\n    {\n      \"n\": 10,\n      \"column\": \"right\",\n      \"text\": \"Ta irr tas KUNGS \\\\\\nwn Wahrd\u1e63 ap\u017ftiprinajs/ \\\\\\nwi\ua7a5\u017fch irr runnajs/ jo es e \\\\\\nzeh\u017fces manna Tehwa Dahw \\\\\\nWeeta/ un fehschu us Isr \\\\\\nGohda-Kreh\u017flu/itt ka tas KU \\\\\\nirr runnajs/ un efinu ve \\\\\\nNammu darrijs ta KUNG \\\\\\nDeewa Isra\u00ebta Wahrdam.\"\n    },\n    {\n      \"n\": 11,\n      \"column\": \"right\",\n      \"text\": \"Un tur efinu es to Sc \\\\\\nstn lizzie/ eek\u017fch ka ta KUN \\\\\\nDerriua irr/ ko wi\ua7a5\u017fch ar I \\\\\\net\u0101 Behrneem darrijs.\"\n    },\n    {\n      \"n\": 12,\n      \"column\": \"right\",\n      \"text\": \"Un wi\ua7a5\u017fch \u017ftahweja prece \\\\\\nta KUNGA Altari/ wi\ufb00a \\\\\\n\u017fra\u00ebta Draud\u017fei pretti/ un \\\\\\nplattija fatwas Rohkas.\"\n    },\n    {\n      \"n\": 13,\n      \"column\": \"right\",\n      \"text\": \"Jo Salamans bij we \\\\\\nwarxa Kreh\u017flu darrijs/ un fi \\\\\\nteem Pagalmeeni lizzis pe \\\\\\nOhlektis garri/ un peeza\u015b \\\\\\nlektis plattu/ un trihs Ohla \\\\\\naugstu/ un wi\ua7a5\u017fch \u017ftahweja \\\\\\nto/ un btj Zeltos mettees prece \\\\\\nwi\ufb00as Isra\u00ebta Draud\u017fes/ u \\\\\\nplattija \u017fawas Rohkas \\\\\\nDebbe\ufb01/ un wi\ua7a5\u017fch fazzija:\"\n    },\n    {\n      \"n\": 14,\n      \"column\": \"right\",\n      \"text\": \"KUNGS/ Isr \\\\\\nDeews/ ne weens irr ta \\\\\\nDeews ka tu efi/ Debbefie \\\\\\nwirs Semmes/ kas tu to D\"\n    }\n  ],\n  \"confidence\": \"high\",\n  \"notes\": \"\"\n}", "error": ""}