{"page": 1148, "max_verse": 28, "full_list": [25, 26, 27, 28, 1, 2, 3, 4, 5, 6, 7, 8, 9, 10, 11, 12, 13, 14, 15, 16, 17], "alternatives": [], "chapter_starts_here": false, "confidence": "high", "notes": "", "raw": "{\n  \"verses\": [\n    {\n      \"n\": 25,\n      \"column\": \"left\",\n      \"text\": \"Woj tad ta Drandse pahr\\nwinnu Dsibres turrehs? jsdal-\\nlis tee winnu starp teem Prez-\\nzinekeem?\\n\"\n    },\n    {\n      \"n\": 26,\n      \"column\": \"left\",\n      \"text\": \"Marri tu ar Dsenmukeem\\nwinna Ahdu pischt / jeb ar\\nScheberkti winna Galiwu.\\n\"\n    },\n    {\n      \"n\": 27,\n      \"column\": \"left\",\n      \"text\": \"Rad tu tawu Rohku us\\nwinnu leezi/ tad peeminni tah-\\ndu Karzu effam / ko tu ne pa-\\nspehsi.\\n\"\n    },\n    {\n      \"n\": 28,\n      \"column\": \"left\",\n      \"text\": \"Redsi / winna Zerriba jahs Lahpas/ deggofchas Dsu\\nbuhs weltiga / neggi tas/ kad steles no tahs islezz.\\nwinsch to eeranga weegli ais-\\nscreeu?\\n\"\n    },\n    {\n      \"n\": 1,\n      \"column\": \"left\",\n      \"text\": \"Ne weens irr tik drohsch/\\nkas winnu drihktetu iszelt/ kas\\ntad buhtu/ kas manna Preekscha\\nwarretu pastahweht.\\n\"\n    },\n    {\n      \"n\": 2,\n      \"column\": \"left\",\n      \"text\": \"Kas irr man ko lab pa-\\npreeksch darrijs/ ka man bij tam\\nto atmakfaht ? kas appakich wis-\\nfahm Debbefim irr/ tas peederr\\nman.\\n\"\n    },\n    {\n      \"n\": 3,\n      \"column\": \"left\",\n      \"text\": \"Man arri kluftu ne jazeefch\\nno winnu Lohzekteem / Stipru-\\nma/ un no winna skaista Gihuna.\\n\"\n    },\n    {\n      \"n\": 4,\n      \"column\": \"left\",\n      \"text\": \"Kuefch drihktetu winna\\nDrebbi atklaht? kas warr ar ta-\\nweim Lauschueem pee winna\\nklaht eet?\\n\"\n    },\n    {\n      \"n\": 5,\n      \"column\": \"left\",\n      \"text\": \"Kas warr winna Waiga\\nSchoklus atplehst ? apkahrt\\nwinna Sohbeem irr Jstruhzt-\\nnafhana.\\n\"\n    },\n    {\n      \"n\": 6,\n      \"column\": \"left\",\n      \"text\": \"Winna levni {Swihat\\nka} stipras preekschturranias\\n\"\n    },\n    {\n      \"n\": 7,\n      \"column\": \"right\",\n      \"text\": \"Ween irr tik tuwn pee\\ntreem/ ka Wehjsch starp teem\\nwarr nahkt.\\n\"\n    },\n    {\n      \"n\": 8,\n      \"column\": \"right\",\n      \"text\": \"Tee peelihp zitti pee\\nteen/ un fatturrahs/ ka tee\\nschkirrahs.\\n\"\n    },\n    {\n      \"n\": 9,\n      \"column\": \"right\",\n      \"text\": \"Winna Schkaudifcha\\nspihd ka Gaischums/ un win-\\nAzzis irr fa ta Ausfcta Az-\\nWahki.\\n\"\n    },\n    {\n      \"n\": 10,\n      \"column\": \"right\",\n      \"text\": \"No winna Muttescha\\n\"\n    },\n    {\n      \"n\": 11,\n      \"column\": \"right\",\n      \"text\": \"No winna Nahsim is\\nDuhmi/ittin ka no wehrdosche\\nPohdeem/ un karsteem Katlee\\n\"\n    },\n    {\n      \"n\": 12,\n      \"column\": \"right\",\n      \"text\": \"Winna Dwajcha war\\ntu Ohgles eededsinaht/ un Le\\nmas iseet no winna Muttes.\\n\"\n    },\n    {\n      \"n\": 13,\n      \"column\": \"right\",\n      \"text\": \"Winna Kattis paleek\\nti stiprs / un kad winsch far\\nPreekscha apbehdina/ tas\\n(winnam) Preeks.\\n\"\n    },\n    {\n      \"n\": 14,\n      \"column\": \"right\",\n      \"text\": \"Winna Meefas Lohze\\nkerrahs kohpa/ tee turrahs ze\\nkohpa/ ka ne warr kustinaht.\\n\"\n    },\n    {\n      \"n\": 15,\n      \"column\": \"right\",\n      \"text\": \"Winna Girds irr zee\\nitt ka Akmins / un ka wee\\nGabbals no appakscheja Dsirn\\nAkmina.\\n\"\n    },\n    {\n      \"n\": 16,\n      \"column\": \"right\",\n      \"text\": \"Rad winsch zelfahs/ t\\nbihstahs tee Stipree / ka tee\\ntohp falansiti/ tad tee (no Gre-\\nkeem) schkistahs.\\n\"\n    },\n    {\n      \"n\": 17,\n      \"column\": \"right\",\n      \"text\": \"Rad kas ar Sobbi\\nwinnu aiskarr/ tad tas ne p\\nstahwehs/ ueds arri Schkeb\\nne\\n\"\n    }\n  ],\n  \"confidence\": \"high\",\n  \"notes\": \"\"\n}", "error": ""}