{"page": 1279, "max_verse": 16, "full_list": [7, 8, 1, 1, 2, 3, 4, 5, 6, 7, 8, 9, 10, 11, 12, 13, 14, 15, 16], "alternatives": [], "chapter_starts_here": false, "confidence": "high", "notes": "", "raw": "{\n  \"verses\": [\n    {\n      \"n\": 7,\n      \"column\": \"left\",\n      \"text\": \"Kad es paschu Behdu\\nWidd\u0169 staigaju/ tad darri tu\\nman d\u017fihwu/ tawu Rohku ie\u017fteep\\ntu prett mannu Eenaidneeku\\nDu\u017finibu/ un tawa labba Roh-\\nta palihds man.\\n\"\n    },\n    {\n      \"n\": 8,\n      \"column\": \"left\",\n      \"text\": \"Tas KUNGS to pree\u017fsch\\nmann pabeigs/ tawa Schehla-\\nstiba/ KUNGS/ paleek muh-\\n\u017fchigi/ tawu Rohko Darbu tu\\nne gribbetu pamest.\\n\"\n    },\n    {\n      \"n\": 1,\n      \"column\": \"left\",\n      \"text\": \"Ta CXXXIX. Dseesma.\\nIrr weena Eepreezinaschana\u00df un Lubgfchana\u00df,\\nDseesma Dahwida/ ka Deews wikau ne\\nween tik brihnigi rabbijs/ bet arridsan\\neek\u017fch wiffeem winna Darbeem/ Wahrdeem/\\nDobmaschanahm wi\u017f\u017fur walda: 1/ 5/ 12\\nUn wehle/ ka Deews wikau wehl wairak\\npree\u017f\u017fch wiltigas Mahzibas pa\u017fargagt: 19\\nUn us ihstenu Zeitu waddiht un waldiht\\ngribbetu: 23.\\nWeena Dahwida Dseesma pree\u017f\u017fch ta\\naugsta Dseedataja.\\n\"\n    },\n    {\n      \"n\": 1,\n      \"column\": \"left\",\n      \"text\": \"UNGS/ tu pahrman-\\nbut/ un pasib\u017fti mannis.\\n\"\n    },\n    {\n      \"n\": 2,\n      \"column\": \"left\",\n      \"text\": \"Tu finni mannu\\nGehdeschann un Zelfschann/ tu\\nprohti mannas Dohmas no tah-\\ntenes.\\n\"\n    },\n    {\n      \"n\": 3,\n      \"column\": \"left\",\n      \"text\": \"Lat es eemu jeb gullu/ tad\\nefft tu apfahrt manni/ un i\u017fluh-\\nfo wi\u017f\u017fus mannu\u00df Zeltus.\\n\"\n    },\n    {\n      \"n\": 4,\n      \"column\": \"left\",\n      \"text\": \"Jo ne fahds Wahrd\u00df irr\\nus mannu Mehli/ red\u017fi/ tu\\nKUNGS to wi\u017f\u017fu finnut.\\n\"\n    },\n    {\n      \"n\": 5,\n      \"column\": \"left\",\n      \"text\": \"Tu mettees apfahrt mannu\\nno Bree\u017f\u017fchas un no pakratenes/\\nun turri tawu Rohku pahr man-\\nnim.\\n\"\n    },\n    {\n      \"n\": 6,\n      \"column\": \"left\",\n      \"text\": \"Schi At\u017fihchana irr man\\n\"\n    },\n    {\n      \"n\": 7,\n      \"column\": \"right\",\n      \"text\": \"Kur buhs man no-eek\\npree\u017f\u017fch tawa Garra? un fur\\nbuhs man behgt pree\u017f\u017fch tawa\\nWaiga?\\n\"\n    },\n    {\n      \"n\": 8,\n      \"column\": \"right\",\n      \"text\": \"Rahpschu es us Debbe\u017fsim/\\ntad tu tur effi/ jeb darri\u017fchu es\\nfawu Gultu Ell\u00ea/ rangi/ tu tur\\narri effi.\\n\"\n    },\n    {\n      \"n\": 9,\n      \"column\": \"right\",\n      \"text\": \"Nem\u017fchu es Aufekta\\nSpahrnus/ un palik\u017fchu patt\\nJuhras Gall\u00e3.\\n\"\n    },\n    {\n      \"n\": 10,\n      \"column\": \"right\",\n      \"text\": \"Tad ir tur tawa Rohka\\nmannit waddihs/ un tawa labba-\\nRohka manni turrehs.\\n\"\n    },\n    {\n      \"n\": 11,\n      \"column\": \"right\",\n      \"text\": \"Sazzichu es: La\u0131 Tum-\\nfiba mann apkahj/ tad ir ta\\nNakts apkahrt man gaischa-\\nbuhs.\\n\"\n    },\n    {\n      \"n\": 12,\n      \"column\": \"right\",\n      \"text\": \"Jo ir ta Tumfiba tawa\\nPree\u017f\u017fcha ne irr tunicha/ un ta\\nNakts spiht ka ta Deena/ Tum-\\nfiba irr ta patt ka ta Gaitma.\\n\"\n    },\n    {\n      \"n\": 13,\n      \"column\": \"right\",\n      \"text\": \"Jo tu waldi pahr man-\\nnahm Jh\u017ftim/ tu effi mann\\neek\u017fch mannas Mahtes Meefahin\\nap\u017fedsis.\\n\"\n    },\n    {\n      \"n\": 14,\n      \"column\": \"right\",\n      \"text\": \"Es pateizu tew/ ka es\\ntohti brihnischki esmu darrihts/\\nbrihnigi irr tawi Darbi/ un to\\nmannu Dwehfele gann labbi pa-\\n\u017fihst.\\n\"\n    },\n    {\n      \"n\": 15,\n      \"column\": \"right\",\n      \"text\": \"Manni Kauli tew ne bija\\nap\u017flehpti/ kad es Gleppeniba\\ndarrihts tappu/ kad es ar Loh-\\nzekteem apdarrihts tappu appa-\\nchejas Gemmes Weetas.\\n\"\n    },\n    {\n      \"n\": 16,\n      \"column\": \"right\",\n      \"text\": \"Tawas Azzis red\u017feja\\nmannu wehl ne-i\u017f\u017fkaipcu Pihti/\\nFfff ffft 3 un\u00b3\\n\"\n    }\n  ],\n  \"confidence\": \"high\",\n  \"notes\": \"\"\n}", "error": ""}