{"page": 1306, "max_verse": 25, "full_list": [9, 9, 9, 4, 10, 11, 12, 13, 14, 15, 16, 17, 18, 19, 20, 21, 22, 23, 24, 25], "alternatives": [], "chapter_starts_here": false, "confidence": "high", "notes": "", "raw": "{\n  \"verses\": [\n    {\"n\": 9, \"column\": \"left\", \"text\": \"Ar Baggatibu warr kas\\nfawu Dsihwibu ispirkt/ bet tas\\nNabbags to Lammaschann ne\\ndsird.\"},\n    {\"n\": 9, \"column\": \"right\", \"text\": \"Kad noteek kas zerreh\\ntohp/ tas irr tai Dwehfelei f\"},\n    {\"n\": 9, \"column\": \"left\", \"text\": \"To Taifnu Gaischnuns\\npreezasees/ bet to Besdeewigo\"},\n    {\"n\": 4, \"column\": \"left\", \"text\": \"Lukte apdsiffihs.\"},\n    {\"n\": 10, \"column\": \"left\", \"text\": \"Zaur Lepnihu nahk Ree-\\nschana ween/ bet ta Gndriba\\ndarra apdohmiqus (Laudis.)\"},\n    {\"n\": 11, \"column\": \"left\", \"text\": \"Manta kas zaur Neleeti-\\nbu nahk/ ees Masinna/ bet kas\\nto ar Rohku takrahj/ tas to wai-\\nrohs.\"},\n    {\"n\": 12, \"column\": \"left\", \"text\": \"Zerriba kas kawejahs/\\ngrausch to Sir\u0111i/ bet kad nahk\\nkas gaidihts tohp/ tas irr weens\\nRohks tahs Dsihwibas.\"},\n    {\"n\": 13, \"column\": \"left\", \"text\": \"Kas to Wahrdtu nizzina/\\ntas pats feiw tamaitajahs/ bet\\nfas to Bausli bihstahs/ tam tas\\ntohp atmaksahts.\"},\n    {\"n\": 14, \"column\": \"left\", \"text\": \"Ta Gudra Baufiba irr\\nweena Awots tahs Dsihwibas/\\natka\u0131pt no tahs Nahwes Wal-\\ngeim.\"},\n    {\"n\": 15, \"column\": \"left\", \"text\": \"Labba Mahziba darra\\nLabpatiffchann/ bet to Wiltnee-\\nfu Zefsch darra Sahpes.\"},\n    {\"n\": 16, \"column\": \"left\", \"text\": \"Tas Gndrs darra(fawu\\nDarbu) apdohmigt/ bet weens\\nGettis padarra Gefkibu.\"},\n    {\"n\": 17, \"column\": \"left\", \"text\": \"Weens besdeewigs Wehst-\\nneffis eekrittihs Launuma/ bet\\nweena ustizzigs Wehsts irr wee-\\nna Ahrstes-Sable.\"},\n    {\"n\": 18, \"column\": \"left\", \"text\": \"Kas Palrmahzischann\\natmett/ taim nahk Zukschiba un\"},\n    {\"n\": 19, \"column\": \"right\", \"text\": \"dens/ bet teem Gefkeem irr wo\\nna Negantiba wo Launa attsta\\ntees.\"},\n    {\"n\": 20, \"column\": \"right\", \"text\": \"Kas ar Gudreem tinnah\\ntas taps gudrs/ bet kas to Ge-\\nBeedris irr/ tas taps fatreckt\"},\n    {\"n\": 21, \"column\": \"right\", \"text\": \"Launums dsihfees tee\\nGrebzineekem pakkat/ bet tee\\nTaifneem taps Labbums\\nmaktahts.\"},\n    {\"n\": 22, \"column\": \"right\", \"text\": \"Kas labs irr/ ta Man\\nnahk us Behrnu Behrneem/\\nta Grehzineeka Sagahds to\\npreekfch ta Taitna paturrehts.\"},\n    {\"n\": 23, \"column\": \"right\", \"text\": \"Dands Barribas\\neekfch to Nabbagn Waggahn\\nbet zits eek pohst\u0101 zaur to/\\nwinsch bes Taifnibas irr.\"},\n    {\"n\": 24, \"column\": \"right\", \"text\": \"Kas tawu Rihksti taup\\ntas eenihd fawu Dehlu/ bet\\nwinsu mihle/ tas pahrmahza\\ndrihs.\"},\n    {\"n\": 25, \"column\": \"right\", \"text\": \"Tas Taifnajs chd /\\nmehr winna Dwehfele pee-\\ndahs/ bet to Besdeewigo Wi-\\nders paleek tuksch.\"}\n  ],\n  \"confidence\": \"high\",\n  \"notes\": \"\"\n}", "error": ""}