{"page": 1348, "max_verse": 20, "full_list": [18, 19, 20, 1, 2, 3, 4, 5, 6, 7, 8, 9], "alternatives": [], "chapter_starts_here": false, "confidence": "high", "notes": "", "raw": "{\n  \"verses\": [\n    {\n      \"n\": 18,\n      \"column\": \"left\",\n      \"text\": \"Zaur Kuhtribu pagah-\\nschahs tee Balki/ un zaur stix-\\nkahm Rohkahm pill tas Nains\\nzaurt.\\n\"\n    },\n    {\n      \"n\": 19,\n      \"column\": \"left\",\n      \"text\": \"Dshres tohp darritas\\npar Smeeschann/ un tas Wihs\\neepreeztma tohs Dshwus/ un ta\\nNauda aisbildina wiffu.\\n\"\n    },\n    {\n      \"n\": 20,\n      \"column\": \"left\",\n      \"text\": \"Ne lahdi to Rehnixu ta-\\nwa Sirdi/ un ne lahdi to Bag-\\ngatu tawa gu\u017f\u017fama Kambari/\\njo tee Putnt appak\u017fch Debbes\\naiswedt to Balk\u017fni/ un ta\u017fpahr-\\nnaina Tauta darrihs to Wahr-\\ndu finnamu.\\n\"\n    },\n    {\n      \"n\": 1,\n      \"column\": \"left\",\n      \"text\": \"Uhti tawu Maisi pahr\\nUhdeni/ jo tu atraffi to\\nattak pehz ilgu Laiku.\\n\"\n    },\n    {\n      \"n\": 2,\n      \"column\": \"left\",\n      \"text\": \"Jsdalli ( to ) starp \u017fepti-\\nneem/ jeb arri starp astoxeem/ jo\\ntu ne finnt kahds Launums buhs\\nwirs Semmes.\\n\"\n    },\n    {\n      \"n\": 3,\n      \"column\": \"left\",\n      \"text\": \"Kad tahs Badebbezis pil-\\nnas irr/ tad teletj tahs fitpru\\nLeetu us to Semint/ un ka tas\\nKohksprett Deenas-Widdn/ jeb\\nprett Seemeta- Pu\u017fti krittih\u017f /\\ntar Weet\u00e2/ kur wi\ua7a5\u017fch krittih\u017f /\\ntur wi\ua7a5\u017fch paliks.\\n\"\n    },\n    {\n      \"n\": 4,\n      \"column\": \"left\",\n      \"text\": \"Kas uhs to Wehju man-\\n\"\n    },\n    {\n      \"n\": 5,\n      \"column\": \"right\",\n      \"text\": \"Itt ka tu ne finni/ ka\\nZe\u017fsch ta Wehja irr/ jeb tee\\nKault irr eek\u017fch greuhtas\\nwas Mee\u017fahm/ tapatt ne\u017f\\ntu to Deewa Darbu/ kas to\\nfu darra.\\n\"\n    },\n    {\n      \"n\": 6,\n      \"column\": \"right\",\n      \"text\": \"Rihta fehjt tawu Seh-\\nun ne atrauji tawu Rohku A\\nkar\u00e2/ jo tu ne finni/ kur\u017fch va\\nfi isdohtees/ woj tchtin jeb ta\\nun kaut abbejahds Rohpa la\\nisdohtohs/ tad buhtu tas jo\\nbaks.\\n\"\n    },\n    {\n      \"n\": 7,\n      \"column\": \"right\",\n      \"text\": \"Japrohjam tas Gattchu-\\nirr talde/ un Azzim tikkanis\\nSauli uh\u017fluhkoht.\\n\"\n    },\n    {\n      \"n\": 8,\n      \"column\": \"right\",\n      \"text\": \"Tomehr/ jep\u017fchu tas\\nweks dauds Gaddus dshwo/\\neektch ta wiffa preezajahs/ tad\\nwi\ua7a5\u017fch arri atminn tahs Deen\\ntahs Tumfibus/ jo winno bn\\ndauds/ un wiff/ kas pagahj\\nirr/ tas irr Neceetiba.\\n\"\n    },\n    {\n      \"n\": 9,\n      \"column\": \"right\",\n      \"text\": \"Reezajes Jaune\u017f\u017f ta\\nwa Jaunita/ un lat ta\\nwa Sirds labbu Praha\\ntu turrs tawas Jaunitas Dee\\nnas/ un statga tawas Sirde Ze-\\ntos/ un ka tas tawahm Azzim\\npatihk/ bet finni to/ ka tew\\nDecwe\\n\"\n    }\n  ],\n  \"confidence\": \"high\",\n  \"notes\": \"\"\n}", "error": ""}