{"page": 1606, "max_verse": 16, "full_list": [7, 8, 9, 10, 11, 7, 13, 14, 15, 16], "alternatives": [], "chapter_starts_here": false, "confidence": "high", "notes": "", "raw": "{\n  \"verses\": [\n    {\n      \"n\": 7,\n      \"column\": \"left\",\n      \"text\": \"Un nu/ta\u017faka tas KUNGS\\nZebaot/ tas Isra\u00eb\u017fta Deews: Ka-\\npelhz darrat juhs to leelu Launu-\\nmu prett juhfahm Dwehtelehm?\\nta i\u017fdeldeti tohp juhfu Starp\u00e2\\nWihrs un Seewa/ Behrns un\\nSib\u017fchamajs no Juhda Wid-\\ndu\u017f/ ta ka juhs neneeka pahrt\\natlizzinajat.\\n\"\n    },\n    {\n      \"n\": 8,\n      \"column\": \"left\",\n      \"text\": \"Un apkaitinajat manni\\nzaur juhfu Rohkas Darbeem/\\nun kwehpina\u017fat zitteem Dee-\\nweim Egiptes-Semm\u00ea / turp\\njuhs e\u017ffat gahju\u017fchi par Swe-\\n\u017fchineekem mi\u017ft/ tadeht ka juhs\\npa\u017fchi i\u017fdeldatees/ un tohpat par\\nLahstu/ un Neewaschanu \u017ftarp\\nwi\u017ffahm Semmes Tautahm.\\n\"\n    },\n    {\n      \"n\": 9,\n      \"column\": \"left\",\n      \"text\": \"Effeeet juhs aismirfuschi to\\nBlehdibu juhfu Tehwu/ un tahs\\nBlehraas to Kehnizu no Juhda/\\nun winno Seewu Blehraas/ un\\njuhsas Blehraas/ un juhfu See-\\nwu Blehraas/ ko tee irr darrijschi\\neek\u017fch tahs Semmes Juhda/ un\\nJerusa\u017femes Eelaas?\\n\"\n    },\n    {\n      \"n\": 10,\n      \"column\": \"left\",\n      \"text\": \"Un tomehr tee lihds scho-\\ndeun ne irr \u017fagrau\u017fti/ un ne bih-\\n\u017fahs/ ned\u00df staiga eek\u017fch man-\\nnas Bautlibas/ un manno\u00df Lik-\\nkum\u00f4s/ ko es juhfu Preek\u017fcha/\\nun juhfu Tehwu Preek\u017fcha efmu\\ndewis.\\n\"\n    },\n    {\n      \"n\": 11,\n      \"column\": \"left\",\n      \"text\": \"Tadeht ta takka tas\\nKUNGS Zebaot/ tas Isra\u00ebta\\nDeews: Reds/ Es zel\u017fchn fawu\\nWaigu par Launu prett jums/\\ni\u017fdeldeschn wi\u017ffu Juhdu.\\nUn es atjemschu tohs At-\\nu\u00df no Juhda/ kas fawu\\n\"\n    },\n    {\n      \"n\": 7,\n      \"column\": \"right\",\n      \"text\": \"Waigu irr greesufchi Egip\\nSemm\u00ea eet par Swe\u017fchi\\nkeem tur mi\u017ft/ un teem taps\\n\u017feem Egiptes-Semm\u00ea Gale\\nrihts/ zaur Sohbinn tee kritti\\nzaur Baddu taps teem E\\ndarrihts/ tik labbi Maseem\\nLeeleem/ zaur Sohbinn un z\\nBaddu tee nomirs/ un taps\\nNolahdefchanu/ par I\u017ftrubzt\\n\u017fchanu/ par Lah\u017ftu/ un par D\\nwaschanu.\\n\"\n    },\n    {\n      \"n\": 13,\n      \"column\": \"right\",\n      \"text\": \"Jo es peemekleschu to\\nkas Egiptes-Semm\u00ea d\u017fihwo/\\nka es Jerusa\u017femi e\u017fmu peen\\nlejs zaur Sohbinu/zaur Bad\\nun zaur Mehr.\\n\"\n    },\n    {\n      \"n\": 14,\n      \"column\": \"right\",\n      \"text\": \"Ta ka neweens atsbel\\nno teem Atliffufscheem no J\\nda/ kas atlizzinati irr nahku\\nus Egiptes-Semmi par S\\n\u017fchineekem tur mi\u017ft/ ka tee w\\nretn atgreestees us to Sen\\nJuhda/ uhs kurrenes win\\nDwehfele lauschahs atgreeste\\nun tur d\u017fihwoht/ jo teem ne bu\\natgreestees/ bes ween teem/\\naisbehg.\\n\"\n    },\n    {\n      \"n\": 15,\n      \"column\": \"right\",\n      \"text\": \"Tad atbildeja Jeremiju\\nwi\u017fti Wihti/ kas finnaja faw\\nSeewas zitteem Deeweem kw\\npinajam/ un wi\u017fas Seewa\\nkas tur stahweja leela Pulb\\nlihds ar wi\u017f\u017feim Laudim/ kas\\naiptes-Semm\u00ea eek\u017fch Patr\\nd\u017fihwoja/ un tazzija:\\n\"\n    },\n    {\n      \"n\": 16,\n      \"column\": \"right\",\n      \"text\": \"Pehz ta Wahrd\u00e3/ ko\\nuhs nuums e\u017fti runnajs eek\u017fch\\nKUNGA Wahrd\u00e3/ mehs tew\\ngribbam klaufiht.\\n\"\n    }\n  ],\n  \"confidence\": \"high\",\n  \"notes\": \"\"\n}", "error": ""}