{"page": 1714, "max_verse": 26, "full_list": [14, 15, 16, 17, 18, 19, 20, 21, 22, 23, 24, 25, 26], "alternatives": [], "chapter_starts_here": false, "confidence": "high", "notes": "", "raw": "{\n  \"verses\": [\n    {\n      \"n\": 14,\n      \"column\": \"left\",\n      \"text\": \"14. Tadeht tu ne ehdift wair\u00df\\nZilwekus/ ned\u00df likfi tawus Laudis\\npeedausitees/ fakka tas\\nKungs KUNGS.\\n\"\n    },\n    {\n      \"n\": 15,\n      \"column\": \"left\",\n      \"text\": \"15. Un es ne lik\u00dfu wair\u00df to\\nPaganeo Neewafchann pahr te-\\nwim dfirdeht/ un tu ne neffifi\\nwair\u00df to Lauscho Apmehdifscha-\\nnu/ un ne likfi tawus Laudis\\nwair\u00df peedansitees/ fakka tas\\nKungs KUNGS.\\n\"\n    },\n    {\n      \"n\": 16,\n      \"column\": \"left\",\n      \"text\": \"16. Atfak notikfe ta KUNga\\nWahrds us man/ un fazztja:\\n\"\n    },\n    {\n      \"n\": 17,\n      \"column\": \"left\",\n      \"text\": \"17. Tu Zilweka Behrns/ tas\\nIsra\u00ebta Nains/ kad tee faw\u00e1\\nSemm\u00ea dshwoja/ tad tee to fa-\\ngahnija ar fawa Zetta/ un ar fa-\\nweem Darbeem/ winnu Zetsch\\nbija wann\u00e1 Breeklich\u00e1/ ki ta Ne-\\nfchihstiba weenas fahrnainas\\nSeewas.\\n\"\n    },\n    {\n      \"n\": 18,\n      \"column\": \"left\",\n      \"text\": \"18. Tadeht isgahsu es fawu\\nBahrsibu prett winneem/ ta Af-\\ntins deht/ ko tee eckich Semmes\\nbij islehjuschi/ un winnu Suhdu-\\nDeewu deht/ ar ko tee to bij fa-\\ngahnijscht.\\n\"\n    },\n    {\n      \"n\": 19,\n      \"column\": \"left\",\n      \"text\": \"19. Un es fskaifiju tohs starp\\nteein Paganeeni/ un tee tappe\\nisputtinati Walstis/ es fohdiju\\ntohs pehz winno Zetta/ un pehz\\nwinnu Darbeem.\\n\"\n    },\n    {\n      \"n\": 20,\n      \"column\": \"left\",\n      \"text\": \"20. Kad tee nu pee teein Pa-\\nganeem nahze/ kurp tee bija gah-\\nju\u017fchi/ tad fagahnija tee mannu\\nhtu Wahrdu/ tapehz ka mo\\n\"\n    },\n    {\n      \"n\": 21,\n      \"column\": \"right\",\n      \"text\": \"21. Bet es faudseju ma-\\ntwehta Wahrd\u00e3 deht/, ko tee\\nfra\u00ebka Behrni fagahnija st-\\nteem Paganeem/ kurp tee\\nnahkuschi.\\n\"\n    },\n    {\n      \"n\": 22,\n      \"column\": \"right\",\n      \"text\": \"22. Tapehz fakki us Isra-\\nNamnu: Ta fakka tas Ku-\\nKUNGS: Es to ne darru ju-\\ndeht/ tu Isra\u00ebta Nams/\\nmanna twehta Wahrd\u00e3 deht-\\njuhs e\u017f\u017fat fagahni\u017fcht starp t-\\nPaganeem/ kurp juhs e\u017f\u017fat\\nkuschi.\\n\"\n    },\n    {\n      \"n\": 23,\n      \"column\": \"right\",\n      \"text\": \"23. Jo es swehtischu ma-\\nleelu Wahrd\u0169/ kas starp t-\\nPaganeem irr fagahnihts/\\njuhs winno Widd\u0169 e\u017f\u017fat fa-\\nnijtch. Un tee Pagant fa-\\ntihs/ ka es tas KUNGS ef-\\ntakka tas Kungs KUNGS/\\nEs pee juhs preekich winnu\\nzim tapfchu fivehtihts.\\n\"\n    },\n    {\n      \"n\": 24,\n      \"column\": \"right\",\n      \"text\": \"24. Jo es atweddischu\\nno teem Paganeem/ un tap-\\nnaschu juhs no wi\u017f\u017fahm 2-\\nstim/ un weddischu juhs a-\\njuht\u00e3s Semm\u00eas.\\n\"\n    },\n    {\n      \"n\": 25,\n      \"column\": \"right\",\n      \"text\": \"25. Tad flazzinaschu ee-\\njums fchkihstu Uhdeni/ ka\\nfchkihsti tohpat/ no wi\u017f\u017fahm\\nfu Netchkikhstibahm/ un no\\nfeem juhfu Suhdu-Deer-\\ngribbu ce juhs fchkihstibt.\\n\"\n    },\n    {\n      \"n\": 26,\n      \"column\": \"right\",\n      \"text\": \"26. Un es dohtchu jums\\nnu jaunu Sir\u00f0i/ un weenu\\nnu Garru juhfo Widd\u0169/ u-\\njemschu to akminainn Sir\\n\"\n    }\n  ],\n  \"confidence\": \"high\",\n  \"notes\": \"\"\n}", "error": ""}