{"page": 1868, "max_verse": 28, "full_list": [20, 21, 22, 23, 24, 25, 26, 27, 28, 1, 2, 3, 4], "alternatives": [], "chapter_starts_here": false, "confidence": "high", "notes": "", "raw": "{\n  \"verses\": [\n    {\n      \"n\": 20,\n      \"column\": \"left\",\n      \"text\": \"20. Daudf arridsan no da-\\nfhadeem Laudim pee teem ta-\\npulzinajahs ta patt ka Siffeni\\njeb ka Vihchli wirs Semmes:\\nJo tee ne bija isskuitami preektw\\ntahs leelas Draudses.\\n\"\n    },\n    {\n      \"n\": 21,\n      \"column\": \"left\",\n      \"text\": \"21. Un tee isgabje no Nint-\\nwes treju Deemu Gahjuma prett\\nto Lanbu Bektilet/ un apmet-\\ntahs pee Bektilata/ tuwu peeta\\nKalna/ kas tat augschajat Kiliki-\\njai pa labbo Rohkn gull.\\n\"\n    },\n    {\n      \"n\": 22,\n      \"column\": \"left\",\n      \"text\": \"22. Un wi\ua7a5\u017fch nehme wiffu fa-\\nwu Karra-Spehku/ tohs Kahji-\\nneekus un Jahtneekus/ un fawus\\nRattus/ un pagahje turp us\\ntahm Kalnn-Weetahm.\\n\"\n    },\n    {\n      \"n\": 23,\n      \"column\": \"left\",\n      \"text\": \"23. Un isdeldeja Pudu un\\nLudu/ un tspohstija wiffus Raf-\\nfiterus un J\u017fmaeliterus/kas prett\\nTukfnesi dsihwoja/ tat Semmet\\nKellon prett Deenas-Widdn.\\n\"\n    },\n    {\n      \"n\": 24,\n      \"column\": \"left\",\n      \"text\": \"24. Un wi\ua7a5\u017fch zehlahs pahr to\\nWrattu/ un gahje zaux Meso-\\npotamiju/ un tspohstija wiffue\\naugstus Pilsfahthus/ kas pee tahs\\nUppes Arbonas gulleja/ tamehr\\nnahk lihds Juhrai.\\n\"\n    },\n    {\n      \"n\": 25,\n      \"column\": \"left\",\n      \"text\": \"25. Un wi\ua7a5\u017fch usnehme tahe\\nKilikijas Rohbeschahs/ un isdel-\\ndeja wiffus/ kas tam prettitur-\\nrejahs/ un nahze lihds Joppee\\ntihk.\\nRohbeschahin prett Deenas-\\n\"\n    },\n    {\n      \"n\": 26,\n      \"column\": \"right\",\n      \"text\": \"26. Wi\ua7a5\u017fch avflehdsse arrids-\\nwiffus Midijaniterus/ un eei\\ndsinaja winnu Dsihwoktus/\\nispohtija winnu Laidarus.\\n\"\n    },\n    {\n      \"n\": 27,\n      \"column\": \"right\",\n      \"text\": \"27. Un wi\ua7a5\u017fch nogahje us\\nLaufu Damaskus Kweef-\\nPfanzchanas Latka/ un eeded\\nnaja wiffus winnu Tihrumu\\nun likke fihkus un keelus Lohp-\\nnobaut/ un aptauptja win-\\nPilsfahtus/ pohtija winnu Je-\\nimus/ un nokawe wiffus win-\\nJaunektus ar Sohbina Afmir\\n\"\n    },\n    {\n      \"n\": 28,\n      \"column\": \"right\",\n      \"text\": \"28. Un Bihjafchana un Ba-\\nliba-preektch winna kritte pa-\\nwiffeem/ kas Juhras pu\u017f\u017fe dsi-\\nwoja/ kas Sibdana un Tihru-\\nbija/un kasSur\u00e1 un Okim\u00e1dsi-\\nwoja un pahr wiffjeim Jemmi-\\nnes Eedsihwotajeem; Un tee ka-\\nAsdod\u00e1 un Asklona dsihwoja-\\nbihjajahs tohti preektch winna\\n\"\n    },\n    {\n      \"n\": 1,\n      \"column\": \"right\",\n      \"text\": \"Ta III. Nodalla.\\n1. Ad fuhttja tee Weh-\\nSneschus pee winna\\nVineerigeem WahrDeen\\nun likke fazziht :\\n\"\n    },\n    {\n      \"n\": 2,\n      \"column\": \"right\",\n      \"text\": \"2. Raugi/ mehs Kalpita le-\\nla- Kehnika Nebukadnezara\\nsam tawa Preektcha/ darri\\nmums ka tew patihk.\\n\"\n    },\n    {\n      \"n\": 3,\n      \"column\": \"right\",\n      \"text\": \"3. Raugi/ wiff muhsu Dfi-\\nwokti/un wiffi auglige Tihrum-\\nir fibft un leeli Lohvi/ un wiff-\\nEhkas to Laidaru trr tar-\\nPreeksch\u00e1/ darri/ ta tas tew p\\n\"\n    },\n    {\n      \"n\": 4,\n      \"column\": \"right\",\n      \"text\": \"4. Medsi/ arridsan muh-\\nP\\n\"\n    }\n  ],\n  \"confidence\": \"high\",\n  \"notes\": \"\"\n}", "error": ""}